menu_cli_fz/__init__.py
menu_cli_fz/__main__.py
menu_cli_fz/main.py
menu_cli_fz-0.1.5.dist-info/entry_points.txt
menu_cli_fz-0.1.5.dist-info/METADATA
menu_cli_fz-0.1.5.dist-info/WHEEL
menu_cli_fz-0.1.5.dist-info/RECORD
